saroj_dongol/__init__.py
saroj_dongol/__main__.py
saroj_dongol/speaker.py
saroj_dongol/speakers/__init__.py
saroj_dongol/speakers/saroj.py
saroj_dongol-0.2.0.dist-info/licenses/LICENSE.txt
saroj_dongol-0.2.0.dist-info/METADATA
saroj_dongol-0.2.0.dist-info/WHEEL
saroj_dongol-0.2.0.dist-info/entry_points.txt
saroj_dongol-0.2.0.dist-info/top_level.txt
saroj_dongol-0.2.0.dist-info/RECORD
