Metadata-Version: 2.4
Name: saroj_dongol
Version: 0.2.0
Summary: my first package
Author-email: Saroj DOngol <sarojdongol@gmail.com>
License: Copyright 2025 Saroj Dongol
Project-URL: Homepage, https://github.com/sarojdongol/timebalancer
Project-URL: Documentation, https://github.com/sarojdongol/timebalancer/README.md
Keywords: Furuness
Requires-Python: >=3.9
License-File: LICENSE.txt
Requires-Dist: colorama~=0.0
Provides-Extra: dev
Requires-Dist: twine; extra == "dev"
Requires-Dist: build; extra == "dev"
Dynamic: license-file
